README.md
setup.py
codonpair/__init__.py
codonpair/codonpair.py
codonpair.egg-info/PKG-INFO
codonpair.egg-info/SOURCES.txt
codonpair.egg-info/dependency_links.txt
codonpair.egg-info/entry_points.txt
codonpair.egg-info/requires.txt
codonpair.egg-info/top_level.txt
codonpair.egg-info/zip-safe
test/test_regression.py