Metadata-Version: 2.1
Name: codonpair
Version: 0.1.1
Summary: A Python implementation to calculate codon pair score
Home-page: http://github.com/smsaladi/codonpair
Author: Shyam Saladi
Author-email: saladi@caltech.edu
License: MIT
Platform: UNKNOWN
